ubittool/__init__.py
ubittool/__main__.py
ubittool/cli.py
ubittool/cmds.py
ubittool/gui.py
ubittool/programmer.py
ubittool-0.7.0.dist-info/entry_points.txt
ubittool-0.7.0.dist-info/LICENSE
ubittool-0.7.0.dist-info/WHEEL
ubittool-0.7.0.dist-info/METADATA
ubittool-0.7.0.dist-info/RECORD
