Metadata-Version: 2.1
Name: ubittool
Version: 0.7.0
Summary: Tool to interface with the BBC micro:bit.
Home-page: https://carlosperate.github.io/ubittool/
License: MIT
Keywords: microbit,micro:bit,bbcmicrobit,ubittool
Author: Carlos Pereira Atencio
Author-email: carlosperate@embeddedlog.com
Requires-Python: >=3.6,<3.10
Classifier: Development Status :: 4 - Beta
Classifier: Environment :: Console
Classifier: Environment :: MacOS X
Classifier: Environment :: Win32 (MS Windows)
Classifier: Environment :: X11 Applications
Classifier: Intended Audience :: Developers
Classifier: Intended Audience :: Education
Classifier: Intended Audience :: End Users/Desktop
Classifier: License :: OSI Approved :: MIT License
Classifier: Operating System :: MacOS
Classifier: Operating System :: Microsoft :: Windows
Classifier: Operating System :: POSIX
Classifier: Programming Language :: Python :: 3
Classifier: Programming Language :: Python :: 3.6
Classifier: Programming Language :: Python :: 3.7
Classifier: Programming Language :: Python :: 3.8
Classifier: Programming Language :: Python :: 3.9
Classifier: Topic :: Education
Classifier: Topic :: Software Development :: Embedded Systems
Requires-Dist: IntelHex (>=2.2.1,<3.0.0)
Requires-Dist: click (>=7.0,<8.0)
Requires-Dist: pyocd (==0.19.0)
Requires-Dist: uflash (>=1.1.0,<1.2.1)
Project-URL: Documentation, https://carlosperate.github.io/ubittool/
Project-URL: Repository, https://github.com/carlosperate/ubittool/
